mylib/__init__.py
mylib/hello.py
mylib/version.json
mylib/version.py
mylib_template-0.2.1.dist-info/LICENSE
mylib_template-0.2.1.dist-info/METADATA
mylib_template-0.2.1.dist-info/WHEEL
mylib_template-0.2.1.dist-info/top_level.txt
mylib_template-0.2.1.dist-info/RECORD
