Metadata-Version: 2.1
Name: mylib-template
Version: 0.2.1
Summary: A template for Python projects
Home-page: https://github.com/ccampguilhem/python-project-template
Author: Cédric Campguilhem
Author-email: cedric.campguilhem@gmail.com
License: UNKNOWN
Platform: UNKNOWN
Classifier: Programming Language :: Python :: 3
Classifier: License :: OSI Approved :: MIT License
Classifier: Operating System :: OS Independent
Classifier: Development Status :: 5 - Production/Stable
Classifier: Intended Audience :: Developers
Requires-Python: >=3.6
